s2cli/__init__.py
s2cli/__main__.py
s2cli/cli.py
s2cli/api/__init__.py
s2cli/api/client.py
s2cli/formatters/__init__.py
s2cli/formatters/bibtex.py
s2cli/formatters/json_fmt.py
s2cli/formatters/table.py
s2cli-0.1.1.dist-info/METADATA
s2cli-0.1.1.dist-info/WHEEL
s2cli-0.1.1.dist-info/entry_points.txt
s2cli-0.1.1.dist-info/RECORD
