Metadata-Version: 2.4
Name: s2cli
Version: 0.1.1
Summary: A CLI for Semantic Scholar API - designed for humans and AI agents
Project-URL: Homepage, https://github.com/mrshu/s2cli
Project-URL: Documentation, https://github.com/mrshu/s2cli#readme
Project-URL: Repository, https://github.com/mrshu/s2cli
Author: mrshu
License-Expression: MIT
Keywords: bibtex,citations,cli,papers,research,semantic-scholar
Classifier: Development Status :: 3 - Alpha
Classifier: Environment :: Console
Classifier: Intended Audience :: Science/Research
Classifier: License :: OSI Approved :: MIT License
Classifier: Programming Language :: Python :: 3
Classifier: Programming Language :: Python :: 3.10
Classifier: Programming Language :: Python :: 3.11
Classifier: Programming Language :: Python :: 3.12
Classifier: Topic :: Scientific/Engineering
Requires-Python: >=3.10
Requires-Dist: httpx>=0.25.0
Requires-Dist: rich>=13.0.0
Requires-Dist: typer>=0.9.0
Provides-Extra: dev
Requires-Dist: pytest-httpx>=0.21.0; extra == 'dev'
Requires-Dist: pytest>=7.0.0; extra == 'dev'
Requires-Dist: ruff>=0.1.0; extra == 'dev'
